gpuprefetch/__init__.py
gpuprefetch/prefetch.py
gpuprefetch/worker.py
gpuprefetch-0.1.0.dist-info/licenses/LICENSE
gpuprefetch-0.1.0.dist-info/METADATA
gpuprefetch-0.1.0.dist-info/WHEEL
gpuprefetch-0.1.0.dist-info/top_level.txt
gpuprefetch-0.1.0.dist-info/RECORD
