Metadata-Version: 2.4
Name: gpuprefetch
Version: 0.1.0
Summary: Package for data prefetching on GPU.
Home-page: http://github.com/antonioterpin/gpu-prefetch
Author: Antonio Terpin
Author-email: aterpin@ethz.ch
Classifier: Intended Audience :: Science/Research
Classifier: License :: OSI Approved :: MIT License
Classifier: Programming Language :: Python :: 3
License-File: LICENSE
Requires-Dist: cupy-cuda12x
Provides-Extra: dev
Requires-Dist: pytest; extra == "dev"
Requires-Dist: setuptools; extra == "dev"
Dynamic: author
Dynamic: author-email
Dynamic: classifier
Dynamic: description
Dynamic: description-content-type
Dynamic: home-page
Dynamic: license-file
Dynamic: provides-extra
Dynamic: requires-dist
Dynamic: summary
